{
    "whoIAm": "Executor",
    "version": 1,
    "contextsLocal": [
        {
            "type": "spawnerState",
            "list": [
                "state"
            ]
        },
        {
            "type": "spawnerParameters",
            "list": [
                "parameters"
            ]
        }
    ],
    "contextsShared": [
        {
            "type": "playerWorldState",
            "list": [
                "playerWorldState"
            ]
        }
    ],
    "contextsToFlush": [
        "toSpawn"
    ],
    "contextsWriteTo": [
        {
            "type": "enemies",
            "list": [
                "toSpawn"
            ]
        },
        {
            "type": "itemsCmds",
            "list": [
                "itemsCmds"
            ]
        }
    ]
}
